morca/__init__.py
morca/core/__init__.py
morca/core/output.py
morca/core/parsers/__init__.py
morca/core/parsers/absorption_spectrum.py
morca/core/parsers/active_space_orbitals.py
morca/core/parsers/charge.py
morca/core/parsers/excited_states.py
morca/core/parsers/geometry.py
morca/core/parsers/imaginary_modes.py
morca/core/parsers/ir_spectrum.py
morca/core/parsers/loewdin_orbital_composition.py
morca/core/parsers/mult.py
morca/core/parsers/n_roots.py
morca/core/parsers/orbital_energies.py
morca/core/parsers/run_time.py
morca/core/parsers/soc_absorption_spectrum.py
morca/core/parsers/soc_states.py
morca/core/parsers/tda.py
morca/core/parsers/thermodynamics.py
morca/core/parsers/utilities.py
morca/processing/__init__.py
morca/processing/broadening.py
morca/utils/__init__.py
morca/visualization/__init__.py
morca/visualization/simulated_chart.py
morca/visualization/simulated_fig.py
morca/visualization/apps/__init__.py
morca/visualization/apps/app.py
morca/visualization/apps/index.py
morca/visualization/apps/new_orbitals.py
morca/visualization/apps/orbitals.py
morca/visualization/apps/soc_tddft.py
morca/visualization/apps/tddft.py
morca-0.4.3.dist-info/METADATA
morca-0.4.3.dist-info/WHEEL
morca-0.4.3.dist-info/entry_points.txt
morca-0.4.3.dist-info/RECORD
