Metadata-Version: 2.4
Name: morca
Version: 0.4.3
Summary: marimo tools for ORCA calculations
Project-URL: repository, https://codeberg.org/crabby/morca
Requires-Python: >=3.11
Requires-Dist: altair>=5.5.0
Requires-Dist: cotwo>=1.1.12
Requires-Dist: fastapi>=0.115.12
Requires-Dist: marimo>=0.12.4
Requires-Dist: plotly>=6.1.0
Requires-Dist: uvicorn>=0.34.2
Requires-Dist: vegafusion>=2.0.2
Requires-Dist: vl-convert-python>=1.7.0
